hokireceh_claimer/__init__.py
hokireceh_claimer/base.py
hokireceh_claimer-0.1.2.dist-info/LICENSE
hokireceh_claimer-0.1.2.dist-info/METADATA
hokireceh_claimer-0.1.2.dist-info/WHEEL
hokireceh_claimer-0.1.2.dist-info/top_level.txt
hokireceh_claimer-0.1.2.dist-info/RECORD
